{
  "sampleWithOdds": 63,
  "favorite": {
    "bets": 63,
    "wins": 40,
    "winRate": 63,
    "pnl": 1.83,
    "yield": 2.9
  },
  "value": {
    "bets": 13,
    "wins": 7,
    "winRate": 54,
    "pnl": 1.58,
    "yield": 12.2
  },
  "valueStrict": {
    "bets": 6,
    "wins": 4,
    "winRate": 67,
    "pnl": 1.87,
    "yield": 31.2
  },
  "topValue": [
    {
      "home": "Belgium",
      "away": "Senegal",
      "date": "2026-07-01 13:00 UTC-7",
      "label": "Victoire Belgium",
      "prob": 0.7467,
      "odd": 2.2,
      "implied": 0.4545,
      "edge": 0.2922,
      "ev": 0.643,
      "provider": "DraftKings",
      "market": "1N2",
      "lineMovement": 0.0
    },
    {
      "home": "England",
      "away": "DR Congo",
      "date": "2026-07-01 12:00 UTC-4",
      "label": "Plus de 2.5 buts",
      "prob": 0.6991,
      "odd": 1.909,
      "implied": 0.5238,
      "edge": 0.1753,
      "ev": 0.335,
      "provider": "DraftKings",
      "market": "O/U"
    },
    {
      "home": "Belgium",
      "away": "Senegal",
      "date": "2026-07-01 13:00 UTC-7",
      "label": "Plus de 2.5 buts",
      "prob": 0.6267,
      "odd": 2.1,
      "implied": 0.4762,
      "edge": 0.1505,
      "ev": 0.316,
      "provider": "DraftKings",
      "market": "O/U"
    }
  ]
}